{
  "type": "minecraft:crafting_shaped",
  "category": "equipment",
  "key": {
    "A": "minecraft:iron_ingot",
    "C": "minecraft:tripwire_hook"
  },
  "pattern": [
    "AA",
    " C"
  ],
  "result": {
    "count": 1,
    "id": "minecraft:music_disc_chirp",
    "components": {
      "minecraft:attribute_modifiers": [
        {
          "amount": 3,
          "id": "jongs:ranged_weapons.mainhand.attack_damage",
          "slot": "mainhand",
          "type": "minecraft:attack_damage",
          "operation": "add_value"
        },
        {
          "amount": -0.4,
          "id": "jongs:ranged_weapons.mainhand.attack_speed",
          "slot": "mainhand",
          "type": "minecraft:attack_speed",
          "operation": "add_multiplied_base"
        },
        {
          "amount": 0.6,
          "id": "jongs:ranged_weapons.mainhand.sneaking_speed",
          "slot": "mainhand",
          "type": "minecraft:sneaking_speed",
          "operation": "add_multiplied_base"
        }
      ],
      "!minecraft:jukebox_playable": {},
      "minecraft:max_damage": 17,
      "minecraft:damage": 0,
      "minecraft:tooltip_display": {"hidden_components":["minecraft:attribute_modifiers"]},
      "minecraft:use_effects": {"can_sprint":true, "speed_multiplier":1},
      "minecraft:item_model": "jongs:ranged_weapons/pistol",
      "minecraft:item_name": {"translate":"jongs.ranged_weapons.pistol","color":"#00FFFF","bold":true,"shadow_color":[0,0,0,1]},
      "minecraft:lore": [{"translate":"jongs.ranged_weapons.pistol.desc","color":"#00AAAA","italic":false}],
      "minecraft:max_stack_size": 1,
      "minecraft:consumable": {"consume_seconds":2147483647,"animation":"spear","sound":{"sound_id":""},"has_consume_particles":false},
      "minecraft:rarity": "epic",
      "minecraft:tool": {
        "damage_per_block":0,
        "rules": [
          {"blocks":"#minecraft:mineable/axe","speed":2,"correct_for_drops":false}
        ]
      },
      "minecraft:custom_data": {"jongs":[{"purpose":"ranged_weapons.guns"},{"purpose":"ranged_weapons.pistol"}]}
    }
  }
}
