{
  "pools": [
    {
      "bonus_rolls": 0.0,
      "entries": [
        {
          "type": "minecraft:item",
          "functions": [
            {
              "add": false,
              "enchantments": {
                "minecraft:sharpness": 1
              },
              "function": "minecraft:set_enchantments"
            }
          ],
          "name": "minecraft:copper_sword",
          "weight": 6
        },
        {
          "type": "minecraft:item",
          "functions": [
            {
              "add": false,
              "enchantments": {
                "minecraft:looting": 1
              },
              "function": "minecraft:set_enchantments"
            }
          ],
          "name": "minecraft:copper_sword",
          "weight": 6
        },
        {
          "type": "minecraft:item",
          "functions": [
            {
              "add": false,
              "enchantments": {
                "minecraft:knockback": 1
              },
              "function": "minecraft:set_enchantments"
            }
          ],
          "name": "minecraft:copper_sword",
          "weight": 6
        },
        {
          "type": "minecraft:item",
          "functions": [
            {
              "add": false,
              "enchantments": {
                "minecraft:unbreaking": 1
              },
              "function": "minecraft:set_enchantments"
            }
          ],
          "name": "minecraft:copper_sword",
          "weight": 6
        },
        {
          "type": "minecraft:item",
          "functions": [
            {
              "add": false,
              "enchantments": {
                "minecraft:sharpness": 5,
                "minecraft:sweeping_edge": 3,
                "minecraft:unbreaking": 3,
                "minecraft:mending": 1
              },
              "function": "minecraft:set_enchantments"
            },
            {
              "components": {
                "minecraft:rarity": "epic"
              },
              "function": "minecraft:set_components"
            }
          ],
          "name": "minecraft:copper_sword",
          "weight": 1
        }
      ],
      "rolls": 1.0
    },
    {
      "bonus_rolls": 0.0,
      "entries": [
        {
          "type": "minecraft:item",
          "functions": [
            {
              "add": false,
              "enchantments": {
                "minecraft:efficiency": 1
              },
              "function": "minecraft:set_enchantments"
            }
          ],
          "name": "minecraft:copper_axe",
          "weight": 1
        },
        {
          "type": "minecraft:item",
          "functions": [
            {
              "add": false,
              "enchantments": {
                "minecraft:sharpness": 1
              },
              "function": "minecraft:set_enchantments"
            }
          ],
          "name": "minecraft:copper_axe",
          "weight": 1
        },
        {
          "type": "minecraft:item",
          "functions": [
            {
              "add": false,
              "enchantments": {
                "minecraft:unbreaking": 1
              },
              "function": "minecraft:set_enchantments"
            }
          ],
          "name": "minecraft:copper_axe",
          "weight": 1
        }
      ],
      "rolls": 1.0
    },
    {
      "bonus_rolls": 0.0,
      "entries": [
        {
          "type": "minecraft:item",
          "functions": [
            {
              "add": false,
              "enchantments": {
                "minecraft:efficiency": 1
              },
              "function": "minecraft:set_enchantments"
            }
          ],
          "name": "minecraft:copper_pickaxe",
          "weight": 1
        },
        {
          "type": "minecraft:item",
          "functions": [
            {
              "add": false,
              "enchantments": {
                "minecraft:fortune": 1
              },
              "function": "minecraft:set_enchantments"
            }
          ],
          "name": "minecraft:copper_pickaxe",
          "weight": 1
        },
        {
          "type": "minecraft:item",
          "functions": [
            {
              "add": false,
              "enchantments": {
                "minecraft:unbreaking": 1
              },
              "function": "minecraft:set_enchantments"
            }
          ],
          "name": "minecraft:copper_pickaxe",
          "weight": 1
        }
      ],
      "rolls": 1.0
    },
    {
      "bonus_rolls": 0.0,
      "entries": [
        {
          "type": "minecraft:item",
          "functions": [
            {
              "add": false,
              "count": {
                "type": "minecraft:uniform",
                "max": 12.0,
                "min": 8.0
              },
              "function": "minecraft:set_count"
            }
          ],
          "name": "minecraft:cooked_chicken",
          "weight": 8
        },
        {
          "type": "minecraft:item",
          "functions": [
            {
              "add": false,
              "count": {
                "type": "minecraft:uniform",
                "max": 12.0,
                "min": 8.0
              },
              "function": "minecraft:set_count"
            }
          ],
          "name": "minecraft:baked_potato",
          "weight": 9
        },
        {
          "type": "minecraft:item",
          "functions": [
            {
              "add": false,
              "count": {
                "type": "minecraft:uniform",
                "max": 12.0,
                "min": 8.0
              },
              "function": "minecraft:set_count"
            }
          ],
          "name": "minecraft:bread",
          "weight": 9
        },
        {
          "type": "minecraft:item",
          "functions": [
            {
              "add": false,
              "count": {
                "type": "minecraft:uniform",
                "max": 12.0,
                "min": 8.0
              },
              "function": "minecraft:set_count"
            }
          ],
          "name": "minecraft:cooked_cod",
          "weight": 9
        },
        {
          "type": "minecraft:item",
          "functions": [
            {
              "add": false,
              "count": {
                "type": "minecraft:uniform",
                "max": 12.0,
                "min": 8.0
              },
              "function": "minecraft:set_count"
            }
          ],
          "name": "minecraft:cooked_rabbit",
          "weight": 9
        },
        {
          "type": "minecraft:item",
          "functions": [
            {
              "add": false,
              "count": {
                "type": "minecraft:uniform",
                "max": 12.0,
                "min": 8.0
              },
              "function": "minecraft:set_count"
            }
          ],
          "name": "minecraft:apple",
          "weight": 14
        },
        {
          "type": "minecraft:item",
          "functions": [
            {
              "add": false,
              "count": {
                "type": "minecraft:uniform",
                "max": 12.0,
                "min": 8.0
              },
              "function": "minecraft:set_count"
            }
          ],
          "name": "minecraft:carrot",
          "weight": 14
        }
      ],
      "rolls": 3.0
    },
    {
      "bonus_rolls": 0.0,
      "entries": [
        {
          "type": "minecraft:item",
          "functions": [
            {
              "add": false,
              "count": {
                "type": "minecraft:uniform",
                "max": 36.0,
                "min": 24.0
              },
              "function": "minecraft:set_count"
            }
          ],
          "name": "minecraft:torch",
          "weight": 1
        }
      ],
      "rolls": 1.0
    },
    {
      "bonus_rolls": 0.0,
      "entries": [
        {
          "type": "minecraft:item",
          "functions": [
            {
              "add": false,
              "count": {
                "type": "minecraft:uniform",
                "max": 32.0,
                "min": 16.0
              },
              "function": "minecraft:set_count"
            }
          ],
          "name": "minecraft:oak_planks",
          "weight": 1
        }
      ],
      "rolls": 1.0
    }
  ]
}